{
    "Ar36": {
        "error": 0.0016460513332769633, 
        "filter_outliers_dict": {
            "filter_outliers": true, 
            "iterations": 1, 
            "std_devs": 2
        }, 
        "fit": "Linear", 
        "value": 0.09238084521712768
    }, 
    "Ar37": {
        "error": 0.020584924477346268, 
        "filter_outliers_dict": {
            "filter_outliers": true, 
            "iterations": 1, 
            "std_devs": 2
        }, 
        "fit": "linear", 
        "value": 0.09586723006565605
    }, 
    "Ar38": {
        "error": 0.010040679235603249, 
        "filter_outliers_dict": {
            "filter_outliers": true, 
            "iterations": 1, 
            "std_devs": 2
        }, 
        "fit": "linear", 
        "value": 0.227804473818892
    }, 
    "Ar39": {
        "error": 0.03339721074371753, 
        "filter_outliers_dict": {
            "filter_outliers": true, 
            "iterations": 1, 
            "std_devs": 2
        }, 
        "fit": "Linear", 
        "value": 17.950577908739373
    }, 
    "Ar40": {
        "error": 0.11127161838952306, 
        "filter_outliers_dict": {
            "filter_outliers": true, 
            "iterations": 1, 
            "std_devs": 2
        }, 
        "fit": "Linear", 
        "value": 1116.568531120839
    }, 
    "Ar41": {
        "error": 0.005877085609307738, 
        "filter_outliers_dict": {
            "filter_outliers": true, 
            "iterations": 1, 
            "std_devs": 2
        }, 
        "fit": "Average", 
        "value": 0.0120352307563411
    }
}