{
    "Ar36": {
        "error": 0.00045025373223577723, 
        "filter_outliers_dict": {
            "filter_outliers": true, 
            "iterations": 1, 
            "std_devs": 2
        }, 
        "fit": "Parabolic", 
        "value": 0.04921817690434702
    }, 
    "Ar37": {
        "error": 0.005243005241599144, 
        "filter_outliers_dict": {
            "filter_outliers": true, 
            "iterations": 1, 
            "std_devs": 2
        }, 
        "fit": "linear", 
        "value": 0.03966701214532347
    }, 
    "Ar38": {
        "error": 0.002515690660911795, 
        "filter_outliers_dict": {
            "filter_outliers": true, 
            "iterations": 1, 
            "std_devs": 2
        }, 
        "fit": "linear", 
        "value": 1.2293560960925511
    }, 
    "Ar39": {
        "error": 0.015218539514019695, 
        "filter_outliers_dict": {
            "filter_outliers": true, 
            "iterations": 1, 
            "std_devs": 2
        }, 
        "fit": "Parabolic", 
        "value": 93.30444432206531
    }, 
    "Ar40": {
        "error": 0.052678081362741276, 
        "filter_outliers_dict": {
            "filter_outliers": true, 
            "iterations": 1, 
            "std_devs": 2
        }, 
        "fit": "Parabolic", 
        "value": 1167.7421128064427
    }, 
    "Ar41": {
        "error": 0.003425823844886132, 
        "filter_outliers_dict": {
            "filter_outliers": true, 
            "iterations": 1, 
            "std_devs": 2
        }, 
        "fit": "linear", 
        "value": -0.008366986814885319
    }
}